setup.py
xvarnish/__init__.py
xvarnish_python.egg-info/PKG-INFO
xvarnish_python.egg-info/SOURCES.txt
xvarnish_python.egg-info/dependency_links.txt
xvarnish_python.egg-info/requires.txt
xvarnish_python.egg-info/top_level.txt