Metadata-Version: 1.0
Name: xvarnish-python
Version: 1.0
Summary: A Python package to include pip dependencies for xVarnish.
Home-page: http://xvarnish.com
Author: Bryon Elston
Author-email: bryon@x10hosting.com
License: UNKNOWN
Download-URL: http://staging.xvarnish.com/xvarnish-python-1.0.tar.gz
Platform: UNKNOWN
Classifier: Programming Language :: Python :: 2.6
Classifier: Intended Audience :: Developers
Classifier: License :: OSI Approved :: BSD License
Classifier: Operating System :: OS Independent
Classifier: Topic :: Software Development
